circremote/__init__.py
circremote/cli.py
circremote/config.py
circremote/connection.py
circremote/version.py
circremote/commands/ADT7410/code.py
circremote/commands/ADT7410/info.json
circremote/commands/ADT7410/requirements.txt
circremote/commands/ADXL335/code.py
circremote/commands/ADXL335/info.json
circremote/commands/ADXL335/requirements.txt
circremote/commands/ADXL343/code.py
circremote/commands/ADXL343/info.json
circremote/commands/ADXL343/requirements.txt
circremote/commands/ADXL345/code.py
circremote/commands/ADXL345/info.json
circremote/commands/ADXL345/requirements.txt
circremote/commands/ADXL375/code.py
circremote/commands/ADXL375/info.json
circremote/commands/ADXL375/requirements.txt
circremote/commands/AHT20/code.py
circremote/commands/AHT20/info.json
circremote/commands/AHT20/requirements.txt
circremote/commands/AMG8833/code.py
circremote/commands/AMG8833/info.json
circremote/commands/AMG8833/requirements.txt
circremote/commands/APDS9960/code.py
circremote/commands/APDS9960/info.json
circremote/commands/APDS9960/requirements.txt
circremote/commands/AS7262/code.py
circremote/commands/AS7262/info.json
circremote/commands/AS7262/requirements.txt
circremote/commands/AS7341/code.py
circremote/commands/AS7341/info.json
circremote/commands/AS7341/requirements.txt
circremote/commands/BH1750/code.py
circremote/commands/BH1750/info.json
circremote/commands/BH1750/requirements.txt
circremote/commands/BME280/code.py
circremote/commands/BME280/info.json
circremote/commands/BME280/requirements.txt
circremote/commands/BME680/code.py
circremote/commands/BME680/info.json
circremote/commands/BME680/requirements.txt
circremote/commands/BMP280/code.py
circremote/commands/BMP280/info.json
circremote/commands/BMP280/requirements.txt
circremote/commands/BMP3XX/code.py
circremote/commands/BMP3XX/info.json
circremote/commands/BMP3XX/requirements.txt
circremote/commands/BNO055/code.py
circremote/commands/BNO055/info.json
circremote/commands/BNO055/requirements.txt
circremote-0.12.0.dist-info/licenses/LICENSE
circremote-0.12.0.dist-info/METADATA
circremote-0.12.0.dist-info/WHEEL
circremote-0.12.0.dist-info/entry_points.txt
circremote-0.12.0.dist-info/top_level.txt
circremote-0.12.0.dist-info/RECORD
