Metadata-Version: 2.4
Name: circremote
Version: 0.12.0
Summary: A command-line tool for uploading and running code on CircuitPython devices
Author-email: John Romkey <58883+romkey@users.noreply.github.com>
Maintainer-email: John Romkey <58883+romkey@users.noreply.github.com>
License-Expression: MIT
Project-URL: Homepage, https://github.com/romkey/circremote
Project-URL: Documentation, https://github.com/romkey/circremote#readme
Project-URL: Repository, https://github.com/romkey/circremote
Project-URL: Bug Tracker, https://github.com/romkey/circremote/issues
Project-URL: Changelog, https://github.com/romkey/circremote/blob/main/CHANGELOG.md
Keywords: circuitpython,microcontroller,serial,websocket,webworkflow,esp32,sensors
Classifier: Development Status :: 5 - Production/Stable
Classifier: Intended Audience :: Developers
Classifier: Operating System :: OS Independent
Classifier: Programming Language :: Python :: 3
Classifier: Programming Language :: Python :: 3.10
Classifier: Programming Language :: Python :: 3.11
Classifier: Programming Language :: Python :: 3.12
Classifier: Topic :: Software Development :: Libraries :: Python Modules
Classifier: Topic :: System :: Hardware
Classifier: Topic :: Utilities
Requires-Python: >=3.7
License-File: LICENSE
Requires-Dist: pyserial>=3.5
Requires-Dist: websocket-client>=1.0.0
Requires-Dist: requests>=2.25.0
Requires-Dist: circup>=2.2.2
Provides-Extra: dev
Requires-Dist: pytest>=6.0; extra == "dev"
Requires-Dist: pytest-cov>=2.10; extra == "dev"
Requires-Dist: pytest-mock>=3.0; extra == "dev"
Requires-Dist: tox>=3.0; extra == "dev"
Requires-Dist: flake8>=3.8; extra == "dev"
Requires-Dist: black>=21.0; extra == "dev"
Requires-Dist: isort>=5.0; extra == "dev"
Requires-Dist: sphinx>=3.0; extra == "dev"
Requires-Dist: sphinx-rtd-theme>=0.5; extra == "dev"
Dynamic: license-file
